alto_ds/__init__.py
alto_ds/database.py
alto_ds-1.2023.8.0.dist-info/METADATA
alto_ds-1.2023.8.0.dist-info/WHEEL
alto_ds-1.2023.8.0.dist-info/top_level.txt
alto_ds-1.2023.8.0.dist-info/RECORD
